scons_tool_gnuplot-0.7.4-py3.8-nspkg.pth
sconstool/gnuplot/__init__.py
sconstool/gnuplot/about.py
scons_tool_gnuplot-0.7.4.dist-info/METADATA
scons_tool_gnuplot-0.7.4.dist-info/WHEEL
scons_tool_gnuplot-0.7.4.dist-info/namespace_packages.txt
scons_tool_gnuplot-0.7.4.dist-info/top_level.txt
scons_tool_gnuplot-0.7.4.dist-info/RECORD
