Metadata-Version: 2.1
Name: scons-tool-gnuplot
Version: 0.7.4
Summary: Gnuplot tool for SCons
Home-page: https://github.com/ptomulik/scons-tool-gnuplot
Author: Paweł Tomulik
Author-email: ptomulik@meil.pw.edu.pl
License: UNKNOWN
Platform: UNKNOWN
Requires-Python: >=2.7
